faust/py.typed
faust/events.py
faust/__main__.py
faust/__init__.py
faust/windows.py
faust/worker.py
faust/streams.py
faust/channels.py
faust/auth.py
faust/joins.py
faust/topics.py
faust/exceptions.py
faust/serializers/__init__.py
faust/serializers/codecs.py
faust/serializers/registry.py
faust/serializers/schemas.py
faust/tables/wrappers.py
faust/tables/recovery.py
faust/tables/manager.py
faust/tables/__init__.py
faust/tables/base.py
faust/tables/objects.py
faust/tables/table.py
faust/tables/sets.py
faust/tables/globaltable.py
faust/app/_attached.py
faust/app/__init__.py
faust/app/base.py
faust/app/router.py
faust/types/events.py
faust/types/tables.py
faust/types/web.py
faust/types/transports.py
faust/types/__init__.py
faust/types/windows.py
faust/types/_env.py
faust/types/sensors.py
faust/types/codecs.py
faust/types/fixups.py
faust/types/streams.py
faust/types/agents.py
faust/types/assignor.py
faust/types/tuples.py
faust/types/channels.py
faust/types/core.py
faust/types/stores.py
faust/types/serializers.py
faust/types/enums.py
faust/types/models.py
faust/types/app.py
faust/types/auth.py
faust/types/joins.py
faust/types/router.py
faust/types/topics.py
faust/types/settings/sections.py
faust/types/settings/__init__.py
faust/types/settings/settings.py
faust/types/settings/base.py
faust/types/settings/params.py
faust/agents/actor.py
faust/agents/manager.py
faust/agents/__init__.py
faust/agents/replies.py
faust/agents/agent.py
faust/agents/models.py
faust/sensors/distributed_tracing.py
faust/sensors/statsd.py
faust/sensors/datadog.py
faust/sensors/__init__.py
faust/sensors/prometheus.py
faust/sensors/base.py
faust/sensors/monitor.py
faust/cli/reset.py
faust/cli/tables.py
faust/cli/completion.py
faust/cli/__init__.py
faust/cli/clean_versions.py
faust/cli/base.py
faust/cli/faust.py
faust/cli/worker.py
faust/cli/agents.py
faust/cli/send.py
faust/cli/params.py
faust/cli/models.py
faust_streaming-0.11.3.dist-info/RECORD
faust_streaming-0.11.3.dist-info/METADATA
faust_streaming-0.11.3.dist-info/entry_points.txt
faust_streaming-0.11.3.dist-info/WHEEL
faust_streaming-0.11.3.dist-info/top_level.txt
faust_streaming-0.11.3.dist-info/AUTHORS.md
faust_streaming-0.11.3.dist-info/LICENSE
