Metadata-Version: 2.1
Name: faust-streaming
Version: 0.11.3
Summary: Python Stream processing.
Home-page: UNKNOWN
License: UNKNOWN
Platform: UNKNOWN
Requires-Python: >=3.8.0
Provides-Extra: aiodns
Provides-Extra: aiomonitor
Provides-Extra: cchardet
Provides-Extra: ciso8601
Provides-Extra: cython
Provides-Extra: datadog
Provides-Extra: debug
Provides-Extra: eventlet
Provides-Extra: fast
Provides-Extra: orjson
Provides-Extra: prometheus
Provides-Extra: redis
Provides-Extra: rocksdb
Provides-Extra: rocksdict
Provides-Extra: sentry
Provides-Extra: setproctitle
Provides-Extra: statsd
Provides-Extra: uvloop
Provides-Extra: yaml
License-File: LICENSE
License-File: AUTHORS.md
